HYTechMaster_STT/__init__.py
hytechmaster_stt-0.1.dist-info/METADATA
hytechmaster_stt-0.1.dist-info/WHEEL
hytechmaster_stt-0.1.dist-info/top_level.txt
hytechmaster_stt-0.1.dist-info/RECORD
