Metadata-Version: 2.4
Name: HyTechMaster-STT
Version: 0.1
Summary: this is speech to text packages created by arman rahtore
Author: Arman Rathore
Dynamic: author
Dynamic: summary
